djpyfs/__init__.py
djpyfs/djpyfs.py
djpyfs/models.py
djpyfs/tests.py
django_pyfs-3.2.0.dist-info/LICENSE
django_pyfs-3.2.0.dist-info/METADATA
django_pyfs-3.2.0.dist-info/WHEEL
django_pyfs-3.2.0.dist-info/top_level.txt
django_pyfs-3.2.0.dist-info/RECORD
