Metadata-Version: 2.1
Name: django-pyfs
Version: 3.2.0
Summary: Django pyfilesystem integration
Home-page: https://github.com/edx/django-pyfs
Author: Piotr Mitros
Author-email: pmitros@edx.org
License: Apache 2.0
Platform: UNKNOWN
Classifier: Development Status :: 4 - Beta
Classifier: Framework :: Django
Classifier: Framework :: Django :: 3.2
Classifier: Framework :: Django :: 4.0
Classifier: Programming Language :: Python
Classifier: Programming Language :: Python :: 3
Classifier: Programming Language :: Python :: 3.8
Classifier: Topic :: Software Development :: Libraries :: Python Modules
Classifier: License :: OSI Approved :: Apache Software License
License-File: LICENSE
Requires-Dist: django
Requires-Dist: fs (>=2.0.1)
Requires-Dist: fs-s3fs
